mcp_server_helm/__init__.py
mcp_server_helm/server.py
mcp_server_helm/commands/__init__.py
mcp_server_helm/commands/basic.py
mcp_server_helm/commands/dependencies.py
mcp_server_helm/commands/get.py
mcp_server_helm/commands/package.py
mcp_server_helm/commands/plugin.py
mcp_server_helm/commands/registry.py
mcp_server_helm/commands/release.py
mcp_server_helm/commands/repository.py
mcp_server_helm/commands/search.py
mcp_server_helm/commands/show.py
mcp_server_helm/core/__init__.py
mcp_server_helm/core/server.py
mcp_server_helm/core/utils.py
mcp_server_helm/schemas/__init__.py
mcp_server_helm/schemas/tools.py
mcp_server_helm-0.2.0.post15.dist-info/licenses/LICENSE
mcp_server_helm-0.2.0.post15.dist-info/METADATA
mcp_server_helm-0.2.0.post15.dist-info/WHEEL
mcp_server_helm-0.2.0.post15.dist-info/entry_points.txt
mcp_server_helm-0.2.0.post15.dist-info/top_level.txt
mcp_server_helm-0.2.0.post15.dist-info/RECORD
