Metadata-Version: 2.4
Name: mcp-server-helm
Version: 0.2.0.post15
Summary: MCP server for Helm integration with Claude and other AI assistants
Author-email: Jeff Nasseri <sir.jeff.nasseri@gmail.com>
License: MIT
Classifier: Programming Language :: Python :: 3
Classifier: License :: OSI Approved :: MIT License
Classifier: Operating System :: OS Independent
Requires-Python: >=3.8
License-File: LICENSE
Requires-Dist: mcp-python>=0.1.0
Dynamic: license-file
